gagnatorg/__init__.py
gagnatorg/client.py
gagnatorg/errors.py
gagnatorg-0.1.0.dist-info/METADATA
gagnatorg-0.1.0.dist-info/WHEEL
gagnatorg-0.1.0.dist-info/top_level.txt
gagnatorg-0.1.0.dist-info/RECORD
